sroot.py
sroot-0.0.4.dist-info/LICENCE.txt
sroot-0.0.4.dist-info/METADATA
sroot-0.0.4.dist-info/WHEEL
sroot-0.0.4.dist-info/top_level.txt
sroot-0.0.4.dist-info/RECORD
