Metadata-Version: 2.1
Name: sroot
Version: 0.0.4
Summary: sroot is a Python library for dealing with square root in radical form.
Home-page: UNKNOWN
Author: Aratrik Banerjee
Author-email: baratrik@gmail.comm
License: UNKNOWN
Platform: UNKNOWN
Classifier: Programming Language :: Python :: 3
Classifier: License :: OSI Approved :: MIT License
Classifier: Operating System :: OS Independent
Requires-Python: >=3.6
